<?xml version='1.0'?>
<md.paths version='1.0'>
<metadata_path><internal>true</internal>
<namespace>http://ns.adobe.com/premierePrivateProjectMetaData/1.0/</namespace>
<description>Column.Intrinsic.AudioInfo</description>
<entry_name>Column.Intrinsic.AudioInfo</entry_name>
<parent_id>http://ns.adobe.com/premierePrivateProjectMetaData/1.0/</parent_id>
</metadata_path>
<metadata_path><internal>true</internal>
<namespace>http://ns.adobe.com/premierePrivateProjectMetaData/1.0/</namespace>
<description>Column.Intrinsic.AudioUsage</description>
<entry_name>Column.Intrinsic.AudioUsage</entry_name>
<parent_id>http://ns.adobe.com/premierePrivateProjectMetaData/1.0/</parent_id>
</metadata_path>
<metadata_path><internal>true</internal>
<namespace>http://ns.adobe.com/premierePrivateProjectMetaData/1.0/</namespace>
<description>Column.Intrinsic.MediaTimebase</description>
<entry_name>Column.Intrinsic.MediaTimebase</entry_name>
<parent_id>http://ns.adobe.com/premierePrivateProjectMetaData/1.0/</parent_id>
</metadata_path>
<metadata_path><internal>true</internal>
<namespace>http://ns.adobe.com/premierePrivateProjectMetaData/1.0/</namespace>
<description>Column.Intrinsic.MediaType</description>
<entry_name>Column.Intrinsic.MediaType</entry_name>
<parent_id>http://ns.adobe.com/premierePrivateProjectMetaData/1.0/</parent_id>
</metadata_path>
<metadata_path><internal>false</internal>
<namespace>http://ns.adobe.com/premierePrivateProjectMetaData/1.0/</namespace>
<description>Column.Intrinsic.Name</description>
<entry_name>Column.Intrinsic.Name</entry_name>
<parent_id>http://ns.adobe.com/premierePrivateProjectMetaData/1.0/</parent_id>
</metadata_path>
<metadata_path><internal>true</internal>
<namespace>http://ns.adobe.com/premierePrivateProjectMetaData/1.0/</namespace>
<description>Column.Intrinsic.VideoInfo</description>
<entry_name>Column.Intrinsic.VideoInfo</entry_name>
<parent_id>http://ns.adobe.com/premierePrivateProjectMetaData/1.0/</parent_id>
</metadata_path>
<metadata_path><internal>true</internal>
<namespace>http://ns.adobe.com/premierePrivateProjectMetaData/1.0/</namespace>
<description>Column.Intrinsic.VideoUsage</description>
<entry_name>Column.Intrinsic.VideoUsage</entry_name>
<parent_id>http://ns.adobe.com/premierePrivateProjectMetaData/1.0/</parent_id>
</metadata_path>
<metadata_path><internal>false</internal>
<namespace>http://ns.adobe.com/premierePrivateProjectMetaData/1.0/</namespace>
<description>Column.PropertyText.Codec</description>
<entry_name>Column.PropertyText.Codec</entry_name>
<parent_id>http://ns.adobe.com/premierePrivateProjectMetaData/1.0/</parent_id>
</metadata_path>
<metadata_path><internal>true</internal>
<namespace>http://ns.adobe.com/premierePrivateProjectMetaData/1.0/</namespace>
<description>Column.PropertyText.Label</description>
<entry_name>Column.PropertyText.Label</entry_name>
<parent_id>http://ns.adobe.com/premierePrivateProjectMetaData/1.0/</parent_id>
</metadata_path>
</md.paths>
